acquire_imaging-0.3.1.dist-info/METADATA
acquire_imaging-0.3.1.dist-info/WHEEL
acquire_imaging-0.3.1.dist-info/entry_points.txt
acquire_imaging-0.3.1.dist-info/license_files/LICENSE
acquire/napari.yaml
acquire/acquire.pyi
acquire/__init__.pyi
acquire/__init__.py
acquire/py.typed
acquire/libacquire-driver-common.so
acquire/libacquire-driver-egrabber.so
acquire/libacquire-driver-hdcam.so
acquire/libacquire-driver-pvcam.so
acquire/libacquire-driver-spinnaker.so
acquire/libacquire-driver-zarr.so
acquire/acquire.abi3.so
acquire_imaging-0.3.1.dist-info/RECORD
