Metadata-Version: 2.3
Name: acquire-imaging
Version: 0.3.1
Classifier: Programming Language :: Rust
Classifier: Programming Language :: Python :: Implementation :: CPython
Classifier: Programming Language :: Python :: Implementation :: PyPy
Requires-Dist: numpy >=1.22
Requires-Dist: black ; extra == 'testing'
Requires-Dist: pytest >=7 ; extra == 'testing'
Requires-Dist: mypy ; extra == 'testing'
Requires-Dist: pytest-cov ; extra == 'testing'
Requires-Dist: tifffile ; extra == 'testing'
Requires-Dist: zarr ; extra == 'testing'
Requires-Dist: dask ; extra == 'testing'
Requires-Dist: ome-zarr ; extra == 'testing'
Requires-Dist: ruff ; extra == 'testing'
Requires-Dist: python-dotenv ; extra == 'testing'
Provides-Extra: testing
License-File: LICENSE
Author: Nathan Clack <nclack@chanzuckerberg.com>
Author-email: Nathan Clack <nclack@chanzuckerberg.com>
Requires-Python: >=3.8
